cohort_compare/__init__.py
cohort_compare/data/County_Data_after_impute_after_scaling.csv
cohort_compare/data/us-albers-counties.json
cohort_compare-0.3.1.dist-info/LICENSE.md
cohort_compare-0.3.1.dist-info/METADATA
cohort_compare-0.3.1.dist-info/WHEEL
cohort_compare-0.3.1.dist-info/top_level.txt
cohort_compare-0.3.1.dist-info/RECORD
